{"city":{"id":4930956,"name":"Boston","coord":{"lon":-71.059769,"lat":42.358429},"country":"US","population":0},"cod":"200","message":0.0761,"cnt":10,"list":[{"dt":1461686400,"temp":{"day":39.7,"min":37.81,"max":39.87,"night":38.05,"eve":39.87,"morn":39.7},"pressure":1017.8,"humidity":100,"weather":[{"id":501,"main":"Rain","description":"moderate rain","icon":"10d"}],"speed":7.74,"deg":88,"clouds":92,"rain":5.42},{"dt":1461772800,"temp":{"day":47.71,"min":35.44,"max":55.09,"night":47.17,"eve":55.09,"morn":35.44},"pressure":1025.78,"humidity":73,"weather":[{"id":800,"main":"Clear","description":"clear sky","icon":"01d"}],"speed":4.61,"deg":358,"clouds":0},{"dt":1461859200,"temp":{"day":47.26,"min":39.85,"max":49.64,"night":42.69,"eve":49.24,"morn":39.85},"pressure":1028.24,"humidity":68,"weather":[{"id":800,"main":"Clear","description":"clear sky","icon":"01d"}],"speed":8.5,"deg":6,"clouds":0},{"dt":1461945600,"temp":{"day":55.54,"min":43.79,"max":55.54,"night":45.25,"eve":50.7,"morn":43.79},"pressure":1027.46,"humidity":0,"weather":[{"id":800,"main":"Clear","description":"clear sky","icon":"01d"}],"speed":4.05,"deg":119,"clouds":2},{"dt":1462032000,"temp":{"day":61.43,"min":48,"max":61.43,"night":48,"eve":56.62,"morn":49.87},"pressure":1020.62,"humidity":0,"weather":[{"id":800,"main":"Clear","description":"clear sky","icon":"01d"}],"speed":3.51,"deg":323,"clouds":0},{"dt":1462118400,"temp":{"day":55.56,"min":44.55,"max":55.56,"night":44.55,"eve":53.04,"morn":47.66},"pressure":1029.36,"humidity":0,"weather":[{"id":800,"main":"Clear","description":"clear sky","icon":"01d"}],"speed":6.58,"deg":14,"clouds":0},{"dt":1462204800,"temp":{"day":58.73,"min":47.43,"max":58.73,"night":47.43,"eve":54.01,"morn":48.25},"pressure":1033.19,"humidity":0,"weather":[{"id":800,"main":"Clear","description":"clear sky","icon":"01d"}],"speed":3.6,"deg":70,"clouds":3},{"dt":1462291200,"temp":{"day":53.22,"min":48.83,"max":53.22,"night":49.64,"eve":48.83,"morn":49.66},"pressure":1027.59,"humidity":0,"weather":[{"id":502,"main":"Rain","description":"heavy intensity rain","icon":"10d"}],"speed":4.36,"deg":143,"clouds":96,"rain":18.99},{"dt":1462377600,"temp":{"day":50.29,"min":47.26,"max":50.59,"night":47.26,"eve":47.75,"morn":50.59},"pressure":1013.38,"humidity":0,"weather":[{"id":502,"main":"Rain","description":"heavy intensity rain","icon":"10d"}],"speed":15.08,"deg":58,"clouds":100,"rain":14.56},{"dt":1462464000,"temp":{"day":48.27,"min":43.63,"max":48.27,"night":43.63,"eve":46.04,"morn":46.71},"pressure":1023.68,"humidity":0,"weather":[{"id":500,"main":"Rain","description":"light rain","icon":"10d"}],"speed":15.48,"deg":49,"clouds":69,"rain":1.25}]}